se_community/__init__.py
se_community/community_detection.py
se_community/optimization.py
se_community/structural_entropy.py
structural_entropy_community_detection-0.0.2.dist-info/LICENSE
structural_entropy_community_detection-0.0.2.dist-info/METADATA
structural_entropy_community_detection-0.0.2.dist-info/WHEEL
structural_entropy_community_detection-0.0.2.dist-info/RECORD
