Metadata-Version: 2.1
Name: structural-entropy-community-detection
Version: 0.0.2
Summary: This repository contains the code for structural entropy community detection. The philosophy behind this method is to use the structural entropy of a network to detect communities. The structural entropy is a measure of the uncertainty of the network structure. The idea is that the higher the uncertainty, the more likely it is that the network is divided into communities.
License: MIT
Author: Command M
Author-email: me@c0mm4nd.com
Requires-Python: >=3.10,<4.0
Classifier: License :: OSI Approved :: MIT License
Classifier: Programming Language :: Python :: 3
Classifier: Programming Language :: Python :: 3.10
Classifier: Programming Language :: Python :: 3.11
Classifier: Programming Language :: Python :: 3.12
Requires-Dist: networkx (>=3.3,<4.0)
Requires-Dist: scipy (>=1.14.1,<2.0.0)
